{
  "author": "",
  "category": "",
  "description": "",
  "extensionNamespace": "",
  "fullName": "",
  "helpPath": "",
  "iconUrl": "",
  "name": "AI",
  "previewIconUrl": "",
  "shortDescription": "",
  "version": "",
  "tags": [],
  "authorIds": [],
  "dependencies": [],
  "eventsFunctions": [
    {
      "description": "",
      "fullName": "Make AI Wander",
      "functionType": "Action",
      "group": "",
      "name": "Wander",
      "private": false,
      "sentence": "Make _PARAM1_ Wander",
      "events": [],
      "parameters": [
        {
          "codeOnly": false,
          "defaultValue": "",
          "description": "Object",
          "longDescription": "",
          "name": "obj",
          "optional": false,
          "supplementaryInformation": "",
          "type": "objectList"
        }
      ],
      "objectGroups": []
    }
  ],
  "eventsBasedBehaviors": []
}