{
  "associatedLayout": "Game Scene",
  "lastChangeTimeStamp": 0,
  "name": "Game Manager",
  "events": [
    {
      "disabled": false,
      "folded": false,
      "type": "BuiltinCommonInstructions::Standard",
      "conditions": [
        {
          "type": {
            "inverted": false,
            "value": "KeyPressed"
          },
          "parameters": [
            "",
            "r"
          ],
          "subInstructions": []
        },
        {
          "type": {
            "inverted": false,
            "value": "VarGlobal"
          },
          "parameters": [
            "Level",
            "!=",
            "13"
          ],
          "subInstructions": []
        },
        {
          "type": {
            "inverted": false,
            "value": "BuiltinCommonInstructions::Once"
          },
          "parameters": [],
          "subInstructions": []
        }
      ],
      "actions": [],
      "events": [
        {
          "disabled": false,
          "folded": false,
          "type": "BuiltinCommonInstructions::Standard",
          "conditions": [
            {
              "type": {
                "inverted": false,
                "value": "VarObjetTxt"
              },
              "parameters": [
                "Buttons",
                "Identifier",
                "=",
                "\"Restart\""
              ],
              "subInstructions": []
            }
          ],
          "actions": [
            {
              "type": {
                "inverted": false,
                "value": "ChangeAnimation"
              },
              "parameters": [
                "Buttons",
                "=",
                "3"
              ],
              "subInstructions": []
            },
            {
              "type": {
                "inverted": false,
                "value": "SetObjectVariableAsBoolean"
              },
              "parameters": [
                "Buttons",
                "HeldDownByKey",
                "True"
              ],
              "subInstructions": []
            }
          ],
          "events": [
            {
              "disabled": false,
              "folded": false,
              "type": "BuiltinCommonInstructions::Standard",
              "conditions": [],
              "actions": [
                {
                  "type": {
                    "inverted": false,
                    "value": "Scene"
                  },
                  "parameters": [
                    "",
                    "\"Game Scene\"",
                    "yes"
                  ],
                  "subInstructions": []
                }
              ],
              "events": []
            }
          ]
        }
      ]
    },
    {
      "disabled": false,
      "folded": false,
      "type": "BuiltinCommonInstructions::Standard",
      "conditions": [
        {
          "type": {
            "inverted": false,
            "value": "DepartScene"
          },
          "parameters": [
            ""
          ],
          "subInstructions": []
        },
        {
          "type": {
            "inverted": false,
            "value": "BuiltinCommonInstructions::Once"
          },
          "parameters": [],
          "subInstructions": []
        }
      ],
      "actions": [],
      "events": [
        {
          "disabled": false,
          "folded": false,
          "type": "BuiltinCommonInstructions::Standard",
          "conditions": [],
          "actions": [
            {
              "type": {
                "inverted": false,
                "value": "TextObject::Opacity"
              },
              "parameters": [
                "DeathText",
                "=",
                "0"
              ],
              "subInstructions": []
            },
            {
              "type": {
                "inverted": false,
                "value": "Opacity"
              },
              "parameters": [
                "DeathBackground",
                "=",
                "0"
              ],
              "subInstructions": []
            }
          ],
          "events": []
        },
        {
          "disabled": false,
          "folded": false,
          "type": "BuiltinCommonInstructions::Standard",
          "conditions": [],
          "actions": [
            {
              "type": {
                "inverted": false,
                "value": "MettreXY"
              },
              "parameters": [
                "FadeBackground",
                "=",
                "-16",
                "=",
                "-16"
              ],
              "subInstructions": []
            },
            {
              "type": {
                "inverted": false,
                "value": "Opacity"
              },
              "parameters": [
                "FadeBackground",
                "=",
                "255"
              ],
              "subInstructions": []
            },
            {
              "type": {
                "inverted": false,
                "value": "Tween::AddObjectOpacityTween"
              },
              "parameters": [
                "FadeBackground",
                "Tween",
                "\"appear\"",
                "0",
                "\"easeInQuad\"",
                "750",
                ""
              ],
              "subInstructions": []
            }
          ],
          "events": []
        },
        {
          "disabled": false,
          "folded": false,
          "type": "BuiltinCommonInstructions::Comment",
          "color": {
            "b": 109,
            "g": 230,
            "r": 255,
            "textB": 0,
            "textG": 0,
            "textR": 0
          },
          "comment": "Music",
          "comment2": ""
        },
        {
          "disabled": false,
          "folded": false,
          "type": "BuiltinCommonInstructions::Standard",
          "conditions": [
            {
              "type": {
                "inverted": true,
                "value": "MusicPlaying"
              },
              "parameters": [
                "",
                "1"
              ],
              "subInstructions": []
            }
          ],
          "actions": [
            {
              "type": {
                "inverted": false,
                "value": "PlayMusicCanal"
              },
              "parameters": [
                "",
                "Assets\\Audio\\bgm.mp3",
                "1",
                "yes",
                "50",
                "1"
              ],
              "subInstructions": []
            }
          ],
          "events": []
        }
      ]
    },
    {
      "disabled": false,
      "folded": false,
      "type": "BuiltinCommonInstructions::Comment",
      "color": {
        "b": 109,
        "g": 230,
        "r": 255,
        "textB": 0,
        "textG": 0,
        "textR": 0
      },
      "comment": "Death",
      "comment2": ""
    },
    {
      "disabled": false,
      "folded": false,
      "type": "BuiltinCommonInstructions::Standard",
      "conditions": [
        {
          "type": {
            "inverted": false,
            "value": "SceneVariableAsBoolean"
          },
          "parameters": [
            "PlayerDead",
            "True"
          ],
          "subInstructions": []
        }
      ],
      "actions": [
        {
          "type": {
            "inverted": false,
            "value": "ModVarScene"
          },
          "parameters": [
            "PlayerDeadTimeCount",
            "+",
            "TimeDelta()"
          ],
          "subInstructions": []
        }
      ],
      "events": []
    },
    {
      "disabled": false,
      "folded": false,
      "type": "BuiltinCommonInstructions::Standard",
      "conditions": [
        {
          "type": {
            "inverted": false,
            "value": "SceneVariableAsBoolean"
          },
          "parameters": [
            "PlayerDead",
            "True"
          ],
          "subInstructions": []
        },
        {
          "type": {
            "inverted": false,
            "value": "VarScene"
          },
          "parameters": [
            "PlayerDeadTimeCount",
            "<",
            "1"
          ],
          "subInstructions": []
        }
      ],
      "actions": [],
      "events": [
        {
          "disabled": false,
          "folded": false,
          "type": "BuiltinCommonInstructions::Standard",
          "conditions": [],
          "actions": [
            {
              "type": {
                "inverted": false,
                "value": "ModVolumeMusicCanal"
              },
              "parameters": [
                "",
                "1",
                "=",
                "(1 - Variable(PlayerDeadTimeCount)) * 50"
              ],
              "subInstructions": []
            }
          ],
          "events": []
        }
      ]
    },
    {
      "disabled": false,
      "folded": false,
      "type": "BuiltinCommonInstructions::Standard",
      "conditions": [
        {
          "type": {
            "inverted": false,
            "value": "SceneVariableAsBoolean"
          },
          "parameters": [
            "PlayerDead",
            "True"
          ],
          "subInstructions": []
        },
        {
          "type": {
            "inverted": false,
            "value": "VarScene"
          },
          "parameters": [
            "PlayerDeadTimeCount",
            ">",
            "1"
          ],
          "subInstructions": []
        },
        {
          "type": {
            "inverted": false,
            "value": "BuiltinCommonInstructions::Once"
          },
          "parameters": [],
          "subInstructions": []
        }
      ],
      "actions": [],
      "events": [
        {
          "disabled": false,
          "folded": false,
          "type": "BuiltinCommonInstructions::Standard",
          "conditions": [],
          "actions": [
            {
              "type": {
                "inverted": false,
                "value": "StopMusicCanal"
              },
              "parameters": [
                "",
                "1"
              ],
              "subInstructions": []
            }
          ],
          "events": []
        }
      ]
    },
    {
      "disabled": false,
      "folded": false,
      "type": "BuiltinCommonInstructions::Standard",
      "conditions": [
        {
          "type": {
            "inverted": false,
            "value": "SceneVariableAsBoolean"
          },
          "parameters": [
            "PlayerDead",
            "True"
          ],
          "subInstructions": []
        },
        {
          "type": {
            "inverted": false,
            "value": "VarScene"
          },
          "parameters": [
            "PlayerDeadTimeCount",
            ">",
            "0.75"
          ],
          "subInstructions": []
        },
        {
          "type": {
            "inverted": false,
            "value": "BuiltinCommonInstructions::Once"
          },
          "parameters": [],
          "subInstructions": []
        }
      ],
      "actions": [],
      "events": [
        {
          "disabled": false,
          "folded": false,
          "type": "BuiltinCommonInstructions::Standard",
          "conditions": [],
          "actions": [
            {
              "type": {
                "inverted": false,
                "value": "Tween::AddObjectOpacityTween"
              },
              "parameters": [
                "DeathBackground",
                "Tween",
                "\"FadeIn\"",
                "255",
                "\"linear\"",
                "3000",
                ""
              ],
              "subInstructions": []
            },
            {
              "type": {
                "inverted": false,
                "value": "Tween::AddObjectOpacityTween"
              },
              "parameters": [
                "DeathText",
                "Tween",
                "\"FadeIn\"",
                "255",
                "\"linear\"",
                "3000",
                ""
              ],
              "subInstructions": []
            },
            {
              "type": {
                "inverted": false,
                "value": "Tween::AddObjectScaleTween"
              },
              "parameters": [
                "DeathText",
                "Tween",
                "\"SizeInc\"",
                "1.2",
                "1.2",
                "\"linear\"",
                "6000",
                "",
                "yes"
              ],
              "subInstructions": []
            }
          ],
          "events": []
        },
        {
          "disabled": false,
          "folded": false,
          "type": "BuiltinCommonInstructions::Standard",
          "conditions": [],
          "actions": [
            {
              "type": {
                "inverted": false,
                "value": "PlaySound"
              },
              "parameters": [
                "",
                "Assets\\Audio\\Death Music.mp3",
                "",
                "50",
                "1"
              ],
              "subInstructions": []
            }
          ],
          "events": []
        }
      ]
    },
    {
      "disabled": false,
      "folded": false,
      "type": "BuiltinCommonInstructions::Standard",
      "conditions": [
        {
          "type": {
            "inverted": false,
            "value": "VarScene"
          },
          "parameters": [
            "PlayerDeadTimeCount",
            ">",
            "2"
          ],
          "subInstructions": []
        },
        {
          "type": {
            "inverted": false,
            "value": "BuiltinCommonInstructions::Once"
          },
          "parameters": [],
          "subInstructions": []
        }
      ],
      "actions": [],
      "events": [
        {
          "disabled": false,
          "folded": false,
          "type": "BuiltinCommonInstructions::Standard",
          "conditions": [],
          "actions": [
            {
              "type": {
                "inverted": false,
                "value": "Tween::AddObjectOpacityTween"
              },
              "parameters": [
                "FadeBackground",
                "Tween",
                "\"FadeIn\"",
                "255",
                "\"linear\"",
                "2500",
                ""
              ],
              "subInstructions": []
            }
          ],
          "events": []
        }
      ]
    },
    {
      "disabled": false,
      "folded": false,
      "type": "BuiltinCommonInstructions::Standard",
      "conditions": [
        {
          "type": {
            "inverted": false,
            "value": "VarScene"
          },
          "parameters": [
            "PlayerDeadTimeCount",
            ">",
            "3.75"
          ],
          "subInstructions": []
        },
        {
          "type": {
            "inverted": false,
            "value": "BuiltinCommonInstructions::Once"
          },
          "parameters": [],
          "subInstructions": []
        }
      ],
      "actions": [
        {
          "type": {
            "inverted": false,
            "value": "Tween::AddObjectOpacityTween"
          },
          "parameters": [
            "DeathText",
            "Tween",
            "\"FadeOut\"",
            "64",
            "\"linear\"",
            "3000",
            ""
          ],
          "subInstructions": []
        }
      ],
      "events": []
    },
    {
      "disabled": false,
      "folded": false,
      "type": "BuiltinCommonInstructions::Standard",
      "conditions": [
        {
          "type": {
            "inverted": false,
            "value": "VarScene"
          },
          "parameters": [
            "PlayerDeadTimeCount",
            ">",
            "6"
          ],
          "subInstructions": []
        },
        {
          "type": {
            "inverted": false,
            "value": "BuiltinCommonInstructions::Once"
          },
          "parameters": [],
          "subInstructions": []
        }
      ],
      "actions": [
        {
          "type": {
            "inverted": false,
            "value": "Scene"
          },
          "parameters": [
            "",
            "\"Game Scene\"",
            "yes"
          ],
          "subInstructions": []
        }
      ],
      "events": []
    },
    {
      "disabled": false,
      "folded": false,
      "type": "BuiltinCommonInstructions::Standard",
      "conditions": [],
      "actions": [
        {
          "type": {
            "inverted": false,
            "value": "ModVarScene"
          },
          "parameters": [
            "TimeElapsed",
            "+",
            "TimeDelta()"
          ],
          "subInstructions": []
        }
      ],
      "events": []
    }
  ]
}